pgdedupe/__init__.py
pgdedupe/cli.py
pgdedupe/exact_matches.py
pgdedupe-0.2.1.dist-info/DESCRIPTION.rst
pgdedupe-0.2.1.dist-info/METADATA
pgdedupe-0.2.1.dist-info/RECORD
pgdedupe-0.2.1.dist-info/WHEEL
pgdedupe-0.2.1.dist-info/entry_points.txt
pgdedupe-0.2.1.dist-info/metadata.json
pgdedupe-0.2.1.dist-info/top_level.txt
