Metadata-Version: 2.0
Name: pgdedupe
Version: 0.2.1
Summary: A simple interface to datamade/dedupe to make probabilistic record linkage easy.
Home-page: https://github.com/dssg/pgdedupe
Author: DSaPP Researchers
Author-email: datascifellows@gmail.com
License: MIT license
Keywords: pgdedupe
Platform: UNKNOWN
Classifier: Development Status :: 2 - Pre-Alpha
Classifier: Intended Audience :: Developers
Classifier: License :: OSI Approved :: MIT License
Classifier: Natural Language :: English
Classifier: Programming Language :: Python :: 2
Classifier: Programming Language :: Python :: 2.6
Classifier: Programming Language :: Python :: 2.7
Classifier: Programming Language :: Python :: 3
Classifier: Programming Language :: Python :: 3.3
Classifier: Programming Language :: Python :: 3.4
Classifier: Programming Language :: Python :: 3.5
Requires-Dist: Click (>=6.0)
Requires-Dist: PyYAML
Requires-Dist: dedupe (>=1.6.0)
Requires-Dist: dedupe-variable-name
Requires-Dist: numpy
Requires-Dist: pandas
Requires-Dist: psycopg2
